xpermutations
