Metadata-Version: 1.1
Name: xpermutations
Version: 1.0.1
Summary: Makes permuations; Based on ActiveState recipe 190465
Home-page: http://pypi.python.org/pypi/xpermutations/
Author: James C. Stroud
Author-email: xtald00d@gmail.com
License: BSD (Core code is Creative Commons Attribution 3.0)
Platform: UNKNOWN
Classifier: Programming Language :: Python :: 2.6
Classifier: Programming Language :: Python :: 2.7
